{
  "format": "project-twelve/autotile-rules/v1",
  "fallbackSpriteId": "20",
  "groundSpriteCount": 32,
  "rules": [
    {"spriteId":"0","weight":1,"pattern":[0,0,0,0,1,1,0,1,1]},
    {"spriteId":"1","weight":1,"pattern":[0,0,0,1,1,1,1,1,1]},
    {"spriteId":"2","weight":1,"pattern":[0,0,0,1,1,1,1,1,1]},
    {"spriteId":"3","weight":1,"pattern":[1,1,0,1,1,1,0,1,1]},
    {"spriteId":"4","weight":1,"pattern":[0,1,0,1,1,1,1,1,0]},
    {"spriteId":"5","weight":1,"pattern":[0,1,0,1,1,1,1,1,1]},
    {"spriteId":"6","weight":1,"pattern":[0,0,0,1,1,1,0,1,0]},
    {"spriteId":"7","weight":1,"pattern":[0,0,0,1,1,0,0,1,0]},
    {"spriteId":"8","weight":1,"pattern":[0,1,1,0,1,1,0,1,1]},
    {"spriteId":"9","weight":4,"pattern":[1,1,1,1,1,1,1,1,1]},
    {"spriteId":"10","weight":1,"pattern":[1,1,1,1,1,1,1,1,1]},
    {"spriteId":"11","weight":1,"pattern":[0,1,1,1,1,1,1,1,1]},
    {"spriteId":"12","weight":1,"pattern":[1,1,0,1,1,1,0,1,0]},
    {"spriteId":"13","weight":1,"pattern":[1,1,1,1,1,1,0,1,0]},
    {"spriteId":"14","weight":1,"pattern":[0,1,0,1,1,1,0,0,0]},
    {"spriteId":"15","weight":1,"pattern":[0,1,0,1,1,0,0,0,0]},
    {"spriteId":"16","weight":1,"pattern":[0,1,1,0,1,1,0,0,0]},
    {"spriteId":"17","weight":1,"pattern":[1,1,1,1,1,1,0,0,0]},
    {"spriteId":"18","weight":1,"pattern":[1,1,1,1,1,1,0,1,1]},
    {"spriteId":"19","weight":1,"pattern":[1,1,0,1,1,1,1,1,0]},
    {"spriteId":"20","weight":1,"pattern":[0,0,0,0,1,0,0,0,0]},
    {"spriteId":"21","weight":1,"pattern":[0,1,0,0,1,0,0,1,0]},
    {"spriteId":"22","weight":1,"pattern":[0,1,0,0,1,1,0,1,1]},
    {"spriteId":"23","weight":1,"pattern":[0,0,0,1,1,1,1,1,0]},
    {"spriteId":"24","weight":1,"pattern":[0,0,0,0,1,1,0,0,0]},
    {"spriteId":"25","weight":1,"pattern":[0,0,0,1,1,1,0,0,0]},
    {"spriteId":"26","weight":1,"pattern":[0,1,0,1,1,1,0,1,0]},
    {"spriteId":"27","weight":1,"pattern":[0,1,0,1,1,0,0,1,0]},
    {"spriteId":"28","weight":1,"pattern":[0,0,0,0,1,0,0,1,0]},
    {"spriteId":"29","weight":1,"pattern":[0,1,0,0,1,0,0,0,0]},
    {"spriteId":"30","weight":1,"pattern":[0,1,1,0,1,1,0,1,0]},
    {"spriteId":"31","weight":1,"pattern":[1,1,0,1,1,1,0,0,0]}
  ]
}
